apsbot/__init__.py
apsbot/__main__.py
apsbot/acc.py
apsbot/auth.py
apsbot/bucket.py
apsbot/chat.py
apsbot/cli.py
apsbot/config.py
apsbot/revit.py
apsbot/settings.py
apsbot/tokenconfig.py
apsbot/webhook.py
apsbot-0.3.1.dist-info/METADATA
apsbot-0.3.1.dist-info/WHEEL
apsbot-0.3.1.dist-info/entry_points.txt
apsbot-0.3.1.dist-info/top_level.txt
apsbot-0.3.1.dist-info/RECORD
