Metadata-Version: 2.1
Name: apsbot
Version: 0.3.1
Summary: A simple CLI tool to interact with the Autodesk Forge API.
Home-page: https://github.com/chuongmep/aps-bot.git
Author: chuongmep
Author-email: chuongpqvn@gmail.com
Classifier: Programming Language :: Python :: 3
Classifier: License :: OSI Approved :: MIT License
Classifier: Operating System :: OS Independent
Requires-Python: >=3.9
Requires-Dist: click ==8.1.3
Requires-Dist: aps-toolkit
Requires-Dist: pyperclip ==1.8.2
Requires-Dist: tabulate ==0.9.0
Requires-Dist: openai ==1.33.0
Requires-Dist: langchain-openai ==0.1.8
Requires-Dist: langchain-experimental ==0.0.60
Requires-Dist: langchain ==0.2.3
